fastapi_battery/__init__.py
fastapi_battery/app.py
fastapi_battery/orm.py
fastapi_battery/authorization/__init__.py
fastapi_battery/cors/__init__.py
fastapi_battery/email/__init__.py
fastapi_battery/errata/__init__.py
fastapi_battery/frontend/__init__.py
fastapi_battery/router_mount/__init__.py
fastapi_battery/session/__init__.py
fastapi_battery/spyc_login/__init__.py
fastapi_battery/spyc_login/router.py
fastapi_battery/spyc_login/session.py
fastapi_battery/sqltap/__init__.py
fastapi_battery/static/__init__.py
FastAPI_battery-0.0.4.dist-info/LICENSE
FastAPI_battery-0.0.4.dist-info/METADATA
FastAPI_battery-0.0.4.dist-info/WHEEL
FastAPI_battery-0.0.4.dist-info/top_level.txt
FastAPI_battery-0.0.4.dist-info/RECORD
