Metadata-Version: 2.1
Name: FastAPI-battery
Version: 0.0.4
Summary: Some private battery for FastAPI.
Home-page: https://github.com
Author: d_mok
Author-email: unknown@gmail.com
License: MIT
Platform: UNKNOWN
Classifier: Programming Language :: Python :: 3
Classifier: License :: OSI Approved :: MIT License
Classifier: Operating System :: OS Independent
Requires-Dist: fastapi
Requires-Dist: itsdangerous
Requires-Dist: aiofiles
Requires-Dist: SQLAlchemy
Requires-Dist: sqltap
